nand3.v
module nand3 (Y, A, B, C);
	output Y;
	input A, B, C;
	supply0 GND;
	supply1 PWR;

	pmos(Y, PWR, A);
      	pmos(Y, PWR, B);
		pmos(Y, PWR, C);
	nmos(Y, w1, A);
	nmos(w1, w2, B);
	nmos(w2, GND, C);
endmodule

tb_3_input_nand_gate.v
`timescale 1ns / 1ps
module tb_3_input_nand_gate;
        // Inputs
	reg A, B, C;
        // Outputs
	wire Y;

        // Instantiate the Unit Under Test (UUT)
	nand3 uut (
		.A(A),
		.B(B),
		.C(C),
		.Y(Y)
	);
	
	initial begin
	$dumpfile("tb_3_input_nand_gate.vcd");
	$dumpvars(0,tb_3_input_nand_gate);
	// Initialize Inputs
	A = 0;
	B = 0;
	C = 0;
	#20 $finish;
	end

always #2 A = ~A;
always #1 B = ~B;
always #3 C = ~C;
endmodule

tb_3_input_nand_gate.vcd
$date
	Sun Aug 01 19:20:09 2021
$end
$version
	Icarus Verilog
$end
$timescale
	1ps
$end
$scope module tb_3_input_nand_gate $end
$var wire 1 ! Y $end
$var reg 1 " A $end
$var reg 1 # B $end
$var reg 1 $ C $end
$scope module uut $end
$var wire 1 " A $end
$var wire 1 # B $end
$var wire 1 $ C $end
$var wire 1 % GND $end
$var wire 1 & PWR $end
$var wire 1 ! Y $end
$var wire 1 ' w1 $end
$var wire 1 ( w2 $end
$upscope $end
$upscope $end
$enddefinitions $end
#0
$dumpvars
z(
z'
1&
0%
0$
0#
0"
1!
$end
#1000
z'
1#
#2000
z'
0#
1"
#3000
0!
1#
0'
0(
1$
#4000
z'
0#
1!
0"
#5000
0'
1#
#6000
0#
1"
z'
z(
0$
#7000
z'
1#
#8000
z'
0#
0"
#9000
1#
0'
0(
1$
#10000
z'
0#
1!
1"
#11000
0!
0'
1#
#12000
0#
0"
1!
z'
z(
0$
#13000
z'
1#
#14000
z'
0#
1"
#15000
0!
1#
0'
0(
1$
#16000
z'
0#
1!
0"
#17000
0'
1#
#18000
0#
1"
z'
z(
0$
#19000
z'
1#
#20000
z'
0#
0"
